flace/__init__.py
flace/flace.py
flace/mgrep.py
flace-0.4.0.dist-info/LICENSE
flace-0.4.0.dist-info/METADATA
flace-0.4.0.dist-info/WHEEL
flace-0.4.0.dist-info/top_level.txt
flace-0.4.0.dist-info/RECORD
