Metadata-Version: 2.1
Name: flace
Version: 0.4.0
Summary: flace - Find and repLACE editing tools for python
License: GNU General Public License v3 (GPLv3) (LICENSE)
License-File: LICENSE
